polyphot/__init__.py
polyphot/flux2sfr.py
polyphot/grow_measure.py
polyphot/img2profile.py
polyphot/mask_galex.py
polyphot/mask_image_regions.py
polyphot/polyphot.py
polyphot/radial_profile.py
polyphot-0.1.1.dist-info/METADATA
polyphot-0.1.1.dist-info/WHEEL
polyphot-0.1.1.dist-info/entry_points.txt
polyphot-0.1.1.dist-info/top_level.txt
polyphot-0.1.1.dist-info/RECORD
