Metadata-Version: 2.1
Name: polyphot
Version: 0.1.1
Summary: Extract photometry from arbitrarily-shaped polygons
Author-email: Ralf Kotulla <ralf.kotulla@gmail.com>
Project-URL: Homepage, https://github.com/rkotulla/polyphot
Project-URL: Bug Tracker, https://github.com/rkotulla/polyphot/issues
Classifier: Programming Language :: Python :: 3
Classifier: License :: OSI Approved :: MIT License
Classifier: Operating System :: OS Independent
Requires-Python: >=3.8
Requires-Dist: astropy
Requires-Dist: matplotlib
Requires-Dist: numpy
Requires-Dist: pandas
Requires-Dist: scipy
